<mvc:View 
    controllerName="login.controller.View2"
    xmlns:mvc="sap.ui.core.mvc"
    displayBlock="true"
    xmlns="sap.m"
    xmlns:core="sap.ui.core"
    xmlns:f="sap.f"
	xmlns:card="sap.f.cards"
    xmlns:dnd="sap.ui.core.dnd"
    xmlns:con="login.control"
    
>
    <Shell id="shell">
        <App id="app">
            <pages>
               <Page class="w3-backGround">
              
                 <!-- <Table items="{/Companies}">
						<dragDropConfig>
							<dnd:DragInfo sourceAggregation="items"/>
						</dragDropConfig>
						<columns>
							<Column>
								<header>
									<Text text="CompanyName"/>
								</header>
							</Column>
							<Column>
								<header>
									<Text text="EmployeeCount"/>
								</header>
							</Column>
						</columns>
						<items>
							<ColumnListItem>
								<cells>
									<Text text="{CompanyName}"/>
									<Text text="{EmployeeCount}"/>
								</cells>
							</ColumnListItem>
						</items>
					</Table>
             
                    <content />
                    <footer>
					<Bar>
						<contentMiddle>
							<con:DragDrop id="deleteButtonId" text="Delete" type="Reject" icon="sap-icon://delete" width="30%">
								<con:dragDropConfig>
									<dnd:DropInfo drop="onDrop"/>
								</con:dragDropConfig>
							</con:DragDrop>
						</contentMiddle>
					</Bar>
				</footer> -->
                 <content />
                 <Text text="Current date and Current time"/>
                 <ToolbarSpacer ></ToolbarSpacer>
                 <Label id="oLabel" design="Bold" />
                 
                 <Button text="Next" press="onNext"/>
                
                </Page>
            </pages>
        </App>
    </Shell>
    	
</mvc:View>

